dql/__init__.py
dql/__main__.py
dql/_version.py
dql/cache.py
dql/cli.py
dql/cli_utils.py
dql/dataset.py
dql/error.py
dql/listing.py
dql/loader.py
dql/node.py
dql/nodes_fetcher.py
dql/nodes_thread_pool.py
dql/py.typed
dql/storage.py
dql/utils.py
dql/catalog/__init__.py
dql/catalog/catalog.py
dql/catalog/datasource.py
dql/catalog/formats.py
dql/catalog/loader.py
dql/client/__init__.py
dql/client/azure.py
dql/client/fileslice.py
dql/client/fsspec.py
dql/client/gcs.py
dql/client/local.py
dql/client/s3.py
dql/data_storage/__init__.py
dql/data_storage/abstract.py
dql/data_storage/schema.py
dql/data_storage/sqlite.py
dql/lib/__init__.py
dql/lib/utils.py
dql/lib/webdataset.py
dql/lib/webdataset_meta.py
dql/query/__init__.py
dql/query/batch.py
dql/query/builtins.py
dql/query/dataset.py
dql/query/dispatch.py
dql/query/schema.py
dql/query/udf.py
dql/remote/__init__.py
dql/remote/studio.py
dql/sql/__init__.py
dql/sql/types.py
dql/sql/utils.py
dql/sql/functions/__init__.py
dql/sql/functions/array.py
dql/sql/functions/path.py
dql/sql/sqlite/__init__.py
dql/sql/sqlite/base.py
dql/sql/sqlite/types.py
dql/sql/sqlite/vector.py
dql/vendored/__init__.py
dql/vendored/ast.py
dql/vendored/ast_unparse.py
dql_alpha-0.54.2.dist-info/LICENSE
dql_alpha-0.54.2.dist-info/METADATA
dql_alpha-0.54.2.dist-info/WHEEL
dql_alpha-0.54.2.dist-info/entry_points.txt
dql_alpha-0.54.2.dist-info/top_level.txt
dql_alpha-0.54.2.dist-info/RECORD
