Metadata-Version: 2.1
Name: dql-alpha
Version: 0.54.2
Summary: DQL
Home-page: https://github.com/iterative/dql
Maintainer-email: support@dvc.org
License: Apache-2.0
Platform: any
Classifier: Programming Language :: Python :: 3
Classifier: Programming Language :: Python :: 3.8
Classifier: Programming Language :: Python :: 3.9
Classifier: Programming Language :: Python :: 3.10
Classifier: Programming Language :: Python :: 3.11
Classifier: Development Status :: 2 - Pre-Alpha
Requires-Python: >=3.8
License-File: LICENSE
Requires-Dist: pyyaml
Requires-Dist: tomlkit
Requires-Dist: tqdm
Requires-Dist: reflink
Requires-Dist: python-dateutil >=2
Requires-Dist: attrs >=21.3.0
Requires-Dist: s3fs >=2023.3.0
Requires-Dist: gcsfs >=2023.3.0
Requires-Dist: adlfs >=2023.4.0
Requires-Dist: azure-storage-blob <12.18.0
Requires-Dist: dvc-data >=0.29.0
Requires-Dist: shtab <2,>=1.3.4
Requires-Dist: sqlalchemy <1.5,>=1.4.24
Requires-Dist: multiprocess ==0.70.15
Requires-Dist: dill ==0.3.7
Provides-Extra: dev
Requires-Dist: pandas >=1.4.0 ; extra == 'dev'
Requires-Dist: msgpack <2,>=1.0.4 ; extra == 'dev'
Requires-Dist: requests >=2.22.0 ; extra == 'dev'
Requires-Dist: numpy ; extra == 'dev'
Requires-Dist: scipy ; extra == 'dev'
Requires-Dist: pytest ==7.2.0 ; extra == 'dev'
Requires-Dist: pytest-sugar ==0.9.6 ; extra == 'dev'
Requires-Dist: pytest-cov ==3.0.0 ; extra == 'dev'
Requires-Dist: pytest-mock ==3.8.2 ; extra == 'dev'
Requires-Dist: pytest-servers[all] >=0.2.3 ; extra == 'dev'
Requires-Dist: pytest-benchmark[histogram] ; extra == 'dev'
Requires-Dist: pytest-virtualenv ; extra == 'dev'
Requires-Dist: pytest-asyncio ==0.20.3 ; extra == 'dev'
Requires-Dist: pylint ==2.15.0 ; extra == 'dev'
Requires-Dist: mypy ==0.982 ; extra == 'dev'
Requires-Dist: types-python-dateutil ; extra == 'dev'
Requires-Dist: types-PyYAML ; extra == 'dev'
Requires-Dist: types-requests ; extra == 'dev'
Requires-Dist: dulwich ; extra == 'dev'
Requires-Dist: hypothesis ; extra == 'dev'
Provides-Extra: pandas
Requires-Dist: pandas >=1.4.0 ; extra == 'pandas'
Provides-Extra: remote
Requires-Dist: msgpack <2,>=1.0.4 ; extra == 'remote'
Requires-Dist: requests >=2.22.0 ; extra == 'remote'
Provides-Extra: tests
Requires-Dist: pandas >=1.4.0 ; extra == 'tests'
Requires-Dist: msgpack <2,>=1.0.4 ; extra == 'tests'
Requires-Dist: requests >=2.22.0 ; extra == 'tests'
Requires-Dist: numpy ; extra == 'tests'
Requires-Dist: scipy ; extra == 'tests'
Requires-Dist: pytest ==7.2.0 ; extra == 'tests'
Requires-Dist: pytest-sugar ==0.9.6 ; extra == 'tests'
Requires-Dist: pytest-cov ==3.0.0 ; extra == 'tests'
Requires-Dist: pytest-mock ==3.8.2 ; extra == 'tests'
Requires-Dist: pytest-servers[all] >=0.2.3 ; extra == 'tests'
Requires-Dist: pytest-benchmark[histogram] ; extra == 'tests'
Requires-Dist: pytest-virtualenv ; extra == 'tests'
Requires-Dist: pytest-asyncio ==0.20.3 ; extra == 'tests'
Requires-Dist: pylint ==2.15.0 ; extra == 'tests'
Requires-Dist: mypy ==0.982 ; extra == 'tests'
Requires-Dist: types-python-dateutil ; extra == 'tests'
Requires-Dist: types-PyYAML ; extra == 'tests'
Requires-Dist: types-requests ; extra == 'tests'
Requires-Dist: dulwich ; extra == 'tests'
Requires-Dist: hypothesis ; extra == 'tests'
Provides-Extra: vector
Requires-Dist: numpy ; extra == 'vector'
Requires-Dist: scipy ; extra == 'vector'
